{
  "profile": "local_native_l2",
  "year": 2021,
  "source_commit": "764dd29fad8c1d51b418878d89812e4eb27653f1",
  "base_main_commit": "ecb542afdc266435e18679c2dc04ebca55e85f5b",
  "data_root": "D:/work space/hdata",
  "strategy_file": "母版-20260506-Clone.py",
  "strategy_sha256": "621a9c968473d73dfa1699be0a16714790e4f93ab950957c0a3f88f4f34bcc8e",
  "start_date": "2021-01-01",
  "end_date": "2021-12-31",
  "initial_cash": 1000000,
  "final_value": 3465363.130000002,
  "total_return_pct": 246.536313,
  "trade_count": 448,
  "profile_manifest": {
    "profile": "local_native_l2",
    "disabled_hook_ids": [
      "execution.execution_price_anomalies",
      "execution.fill_amount_anomalies",
      "execution.order_amount_anomalies",
      "execution.preopen_drop_first_duplicate",
      "execution.preopen_reject_cash_below",
      "execution.preopen_reject_orders",
      "market_data.minute_price_anomalies"
    ]
  },
  "hook_telemetry": {
    "execution.preopen_drop_first_duplicate": {
      "queries": 212,
      "effective_hits": 0,
      "would_have_hits": 6,
      "effective_hit_keys": [],
      "first_effective_hit": null,
      "would_have_hit": true,
      "would_have_hit_keys": [
        {
          "date": "2021-04-26",
          "time": "",
          "code": "002120.XSHE",
          "side": "buy",
          "hook_id": "execution.preopen_drop_first_duplicate",
          "effective_hit": false,
          "would_have_hit": true
        },
        {
          "date": "2021-04-26",
          "time": "",
          "code": "002120.XSHE",
          "side": "buy",
          "hook_id": "execution.preopen_drop_first_duplicate",
          "effective_hit": false,
          "would_have_hit": true
        },
        {
          "date": "2021-12-01",
          "time": "",
          "code": "600072.XSHG",
          "side": "buy",
          "hook_id": "execution.preopen_drop_first_duplicate",
          "effective_hit": false,
          "would_have_hit": true
        },
        {
          "date": "2021-12-01",
          "time": "",
          "code": "600072.XSHG",
          "side": "buy",
          "hook_id": "execution.preopen_drop_first_duplicate",
          "effective_hit": false,
          "would_have_hit": true
        },
        {
          "date": "2021-12-08",
          "time": "",
          "code": "002508.XSHE",
          "side": "buy",
          "hook_id": "execution.preopen_drop_first_duplicate",
          "effective_hit": false,
          "would_have_hit": true
        },
        {
          "date": "2021-12-08",
          "time": "",
          "code": "002508.XSHE",
          "side": "buy",
          "hook_id": "execution.preopen_drop_first_duplicate",
          "effective_hit": false,
          "would_have_hit": true
        }
      ],
      "first_would_have_hit": "2021-04-26 ",
      "profile_disabled": true
    },
    "execution.preopen_reject_cash_below": {
      "queries": 212,
      "effective_hits": 0,
      "would_have_hits": 0,
      "effective_hit_keys": [],
      "first_effective_hit": null,
      "would_have_hit": false,
      "would_have_hit_keys": [],
      "first_would_have_hit": null,
      "profile_disabled": true
    },
    "execution.preopen_reject_orders": {
      "queries": 212,
      "effective_hits": 0,
      "would_have_hits": 0,
      "effective_hit_keys": [],
      "first_effective_hit": null,
      "would_have_hit": false,
      "would_have_hit_keys": [],
      "first_would_have_hit": null,
      "profile_disabled": true
    },
    "profile": "local_native_l2"
  }
}